textcrafts/__init__.py
textcrafts/corenlp_api.py
textcrafts/deepRank.py
textcrafts/down.py
textcrafts/parser_api.py
textcrafts/sim.py
textcrafts/stanfordnlp_api.py
textcrafts/vis.py
textcrafts-0.1.2.dist-info/LICENSE
textcrafts-0.1.2.dist-info/METADATA
textcrafts-0.1.2.dist-info/WHEEL
textcrafts-0.1.2.dist-info/top_level.txt
textcrafts-0.1.2.dist-info/RECORD
