Metadata-Version: 2.1
Name: textcrafts
Version: 0.1.2
Summary: textcrafts: Summary, keyphrase and relation extraction with dependecy graphs
Home-page: https://github.com/ptarau/TextGraphCrafts.git
Author: Paul Tarau, Andrea Cortis
License: Apache
Platform: UNKNOWN
Requires-Dist: stanfordnlp (>=0.2.0)
Requires-Dist: graphviz (>=0.13)
Requires-Dist: nltk (>=3.4.5)
Requires-Dist: networkx (>=2.3)
Requires-Dist: wordcloud (>=1.6)
